CHANGES.txt
COPYRIGHT.txt
LICENSE.txt
MANIFEST.in
README.txt
bootstrap.py
buildout.cfg
setup.py
src/tranchitella/__init__.py
src/tranchitella.recipe.testrunner.egg-info/PKG-INFO
src/tranchitella.recipe.testrunner.egg-info/SOURCES.txt
src/tranchitella.recipe.testrunner.egg-info/dependency_links.txt
src/tranchitella.recipe.testrunner.egg-info/entry_points.txt
src/tranchitella.recipe.testrunner.egg-info/namespace_packages.txt
src/tranchitella.recipe.testrunner.egg-info/not-zip-safe
src/tranchitella.recipe.testrunner.egg-info/requires.txt
src/tranchitella.recipe.testrunner.egg-info/top_level.txt
src/tranchitella/recipe/__init__.py
src/tranchitella/recipe/testrunner/README.txt
src/tranchitella/recipe/testrunner/__init__.py
src/tranchitella/recipe/testrunner/tests.py